mcp_server.py
ai_cogence_mcp_server-1.0.0.dist-info/licenses/LICENSE
migrations/__init__.py
migrations/add_geographic_columns.py
ai_cogence_mcp_server-1.0.0.dist-info/METADATA
ai_cogence_mcp_server-1.0.0.dist-info/WHEEL
ai_cogence_mcp_server-1.0.0.dist-info/entry_points.txt
ai_cogence_mcp_server-1.0.0.dist-info/top_level.txt
ai_cogence_mcp_server-1.0.0.dist-info/RECORD
