Metadata-Version: 2.4
Name: ai-cogence-mcp-server
Version: 1.0.0
Summary: MCP (Model Context Protocol) Server for AI Cogence RAG Backend
Author-email: AI Cogence <contact@cogence.ai>
License: MIT
Project-URL: Homepage, https://cogence.ai
Project-URL: Documentation, https://github.com/ai-cogence/mcp-server
Project-URL: Repository, https://github.com/ai-cogence/mcp-server
Project-URL: Issues, https://github.com/ai-cogence/mcp-server/issues
Keywords: mcp,rag,ai,langchain,openai,chatbot,knowledge-base
Classifier: Development Status :: 4 - Beta
Classifier: Intended Audience :: Developers
Classifier: License :: OSI Approved :: MIT License
Classifier: Programming Language :: Python :: 3
Classifier: Programming Language :: Python :: 3.10
Classifier: Programming Language :: Python :: 3.11
Classifier: Programming Language :: Python :: 3.12
Classifier: Programming Language :: Python :: 3.13
Classifier: Topic :: Software Development :: Libraries :: Python Modules
Classifier: Topic :: Scientific/Engineering :: Artificial Intelligence
Requires-Python: >=3.10
License-File: LICENSE
Requires-Dist: mcp>=1.3.2
Requires-Dist: fastapi>=0.116.1
Requires-Dist: langchain>=0.3.27
Requires-Dist: langchain-community>=0.3.27
Requires-Dist: langchain-openai>=0.3.28
Requires-Dist: langchain-postgres>=0.0.15
Requires-Dist: langgraph>=0.2.0
Requires-Dist: langgraph-checkpoint>=2.0.0
Requires-Dist: langgraph-checkpoint-postgres>=2.0.0
Requires-Dist: openai>=1.98.0
Requires-Dist: psycopg>=3.2.9
Requires-Dist: psycopg-pool>=3.2.6
Requires-Dist: pgvector>=0.3.6
Requires-Dist: asyncpg>=0.30.0
Requires-Dist: python-dotenv>=1.0.0
Requires-Dist: uvicorn[standard]>=0.32.1
Provides-Extra: dev
Requires-Dist: pytest>=7.0.0; extra == "dev"
Requires-Dist: pytest-asyncio>=0.21.0; extra == "dev"
Requires-Dist: black>=23.0.0; extra == "dev"
Requires-Dist: isort>=5.12.0; extra == "dev"
Requires-Dist: mypy>=1.0.0; extra == "dev"
Dynamic: license-file
